src/pwm_generator.v
module pwm_generator (
	input clk,
	input rst,
	input [7:0] duty_cycle,
	output reg pwm_out

);

	reg [7:0] counter;
	reg [7:0] duty_cycle_sync;
	
	always @(posedge clk, posedge rst) begin
		if (rst) begin
			counter <= 1'b0;
			duty_cycle_sync <= 1'b0;
			pwm_out <= 1'b0;
		end 	
		else begin
			duty_cycle_sync <= duty_cycle;
			if (counter == 8'b11111111) begin
				counter <= 1'b0;
			end 
			else if (counter < duty_cycle_sync) begin
				pwm_out <= 1'b1;
			end 	
			else begin
				pwm_out <= 1'b0;
				counter <= counter + 1;
			end
			
		end	

	end
	

endmodule

tb/tb_pwm_generator.v
`timescale 1ns/1ns

module tb_pwm_generator ();
	reg clk;
	reg rst;
	reg [7:0]duty_cycle;
	wire pwm_out;
	
	pwm_generator uut (
		.clk(clk),
		.rst(rst),
		.duty_cycle(duty_cycle),
		.pwm_out(pwm_out)
	
	);

	initial begin
		clk = 1'b0;
		forever #1 clk = ~clk;
	end
	
	initial begin
		$monitor("Time= %0t | clk=%b | rst=%b | duty_cycle=%0d | pwm=%b", $time, clk, rst, duty_cycle, pwm_out);
	end

	initial begin 
		$dumpfile("../sim/dump.vcd");
		$dumpvars(0, tb_pwm_generator);
		rst = 1'b1;
		#10;
		rst = 1'b0;
	       	#20
		duty_cycle = 8'b01000000;
		#100;
		duty_cycle = 8'b10000000;
		#100
		rst = 1'b1;
		#20
		rst = 1'b0;
		$finish;
	end

endmodule

sim/dump.vcd
$date
	Sun Mar 22 00:00:59 2026
$end
$version
	Icarus Verilog
$end
$timescale
	1ns
$end
$scope module tb_pwm_generator $end
$var wire 1 ! pwm_out $end
$var reg 1 " clk $end
$var reg 8 # duty_cycle [7:0] $end
$var reg 1 $ rst $end
$scope module uut $end
$var wire 1 " clk $end
$var wire 8 % duty_cycle [7:0] $end
$var wire 1 $ rst $end
$var reg 8 & counter [7:0] $end
$var reg 8 ' duty_cycle_sync [7:0] $end
$var reg 1 ! pwm_out $end
$upscope $end
$upscope $end
$enddefinitions $end
$comment Show the parameter values. $end
$dumpall
$end
#0
$dumpvars
b0 '
b0 &
bx %
1$
bx #
0"
0!
$end
#1
1"
#2
0"
#3
1"
#4
0"
#5
1"
#6
0"
#7
1"
#8
0"
#9
1"
#10
0"
0$
#11
b1 &
bx '
1"
#12
0"
#13
b10 &
1"
#14
0"
#15
b11 &
1"
#16
0"
#17
b100 &
1"
#18
0"
#19
b101 &
1"
#20
0"
#21
b110 &
1"
#22
0"
#23
b111 &
1"
#24
0"
#25
b1000 &
1"
#26
0"
#27
b1001 &
1"
#28
0"
#29
b1010 &
1"
#30
0"
b1000000 #
b1000000 %
#31
b1011 &
b1000000 '
1"
#32
0"
#33
1!
1"
